hb_bank_statement_machine_learning/__init__.py
hb_bank_statement_machine_learning/account.py
hb_bank_statement_machine_learning/bank_ml.py
hb_bank_statement_machine_learning/tryton.cfg
hb_bank_statement_machine_learning/tests/__init__.py
hb_bank_statement_machine_learning/tests/conftest.py
hb_bank_statement_machine_learning/tests/test_ml.py
hb_bank_statement_machine_learning/tests/test_module.py
hb_bank_statement_machine_learning-1.0.0.dist-info/LICENSE
hb_bank_statement_machine_learning-1.0.0.dist-info/METADATA
hb_bank_statement_machine_learning-1.0.0.dist-info/WHEEL
hb_bank_statement_machine_learning-1.0.0.dist-info/entry_points.txt
hb_bank_statement_machine_learning-1.0.0.dist-info/top_level.txt
hb_bank_statement_machine_learning-1.0.0.dist-info/RECORD
